py_tx_queue/__init__.py
py_tx_queue/core/__init__.py
py_tx_queue/core/core.py
py_tx_queue/db/__init__.py
py_tx_queue/db/base.py
py_tx_queue/env/__init__.py
py_tx_queue/migrations/README
py_tx_queue/migrations/alembic.ini
py_tx_queue/migrations/env.py
py_tx_queue/migrations/script.py.mako
py_tx_queue/migrations/versions/2024_11_03_2007-32b70440e82f_v0.py
py_tx_queue-0.2.0.dist-info/METADATA
py_tx_queue-0.2.0.dist-info/WHEEL
py_tx_queue-0.2.0.dist-info/RECORD
